kybra_simple_logging/__init__.py
kybra_simple_logging/_handler.py
kybra_simple_logging/cli.py
kybra_simple_logging-0.2.0.dist-info/licenses/LICENSE
kybra_simple_logging-0.2.0.dist-info/METADATA
kybra_simple_logging-0.2.0.dist-info/WHEEL
kybra_simple_logging-0.2.0.dist-info/entry_points.txt
kybra_simple_logging-0.2.0.dist-info/top_level.txt
kybra_simple_logging-0.2.0.dist-info/RECORD
