Metadata-Version: 2.4
Name: kybra_simple_logging
Version: 0.2.0
Summary: A lightweight logging library for Kybra on the Internet Computer (IC)
Home-page: https://github.com/smart-social-contracts/kybra-simple-logging
Author: Smart Social Contracts
Author-email: Smart Social Contracts <smartsocialcontracts@gmail.com>
License: MIT License
Project-URL: Homepage, https://github.com/smart-social-contracts/kybra-simple-logging
Project-URL: Repository, https://github.com/smart-social-contracts/kybra-simple-logging.git
Project-URL: Issues, https://github.com/smart-social-contracts/kybra-simple-logging/issues
Keywords: logging,debugging,ic,internet-computer
Classifier: Development Status :: 4 - Beta
Classifier: Intended Audience :: Developers
Classifier: License :: OSI Approved :: MIT License
Classifier: Operating System :: OS Independent
Classifier: Programming Language :: Python :: 3
Classifier: Programming Language :: Python :: 3.10
Classifier: Topic :: Database
Classifier: Topic :: Software Development :: Libraries :: Python Modules
Requires-Python: >=3.7
License-File: LICENSE
Dynamic: author
Dynamic: home-page
Dynamic: license-file
Dynamic: requires-python
